{"listOfCourses": [
    {
        "courseName": "CPSC 210",
        "lowestGrade": 0,
        "highestGrade": 0,
        "grade": 0,
        "gradingGroups": [
            {
                "groupName": "MT1",
                "grade": 84,
                "weight": 15
            },
            {
                "groupName": "MT2",
                "grade": 89,
                "weight": 15
            },
            {
                "groupName": "Labs",
                "grade": 100,
                "weight": 10
            },
            {
                "groupName": "Projects",
                "grade": 101,
                "weight": 20
            },
            {
                "groupName": "Tickets",
                "grade": 100,
                "weight": 5
            },
            {
                "groupName": "Final",
                "grade": 99,
                "weight": 0
            }
        ]
    },
    {
        "courseName": "CPSC 121",
        "lowestGrade": 0,
        "highestGrade": 0,
        "grade": 0,
        "gradingGroups": [
            {
                "groupName": "MT1",
                "grade": 84,
                "weight": 14
            },
            {
                "groupName": "MT2",
                "grade": 0,
                "weight": 0
            },
            {
                "groupName": "Quiz",
                "grade": 100,
                "weight": 4
            },
            {
                "groupName": "Labs",
                "grade": 109,
                "weight": 14
            },
            {
                "groupName": "Tutorial",
                "grade": 100,
                "weight": 3
            },
            {
                "groupName": "Clicker",
                "grade": 100,
                "weight": 3
            },
            {
                "groupName": "Final",
                "grade": 100,
                "weight": 0
            },
            {
                "groupName": "Assignments",
                "grade": 100,
                "weight": 0
            }
        ]
    },
    {
        "courseName": "MATH 200",
        "lowestGrade": 0,
        "highestGrade": 0,
        "grade": 0,
        "gradingGroups": [
            {
                "groupName": "MT1",
                "grade": 80,
                "weight": 20
            },
            {
                "groupName": "MT2",
                "grade": 0,
                "weight": 0
            },
            {
                "groupName": "Final",
                "grade": 0,
                "weight": 0
            },
            {
                "groupName": "HW",
                "grade": 100,
                "weight": 10
            }
        ]
    },
    {
        "courseName": "MATH 221",
        "lowestGrade": 0,
        "highestGrade": 0,
        "grade": 0,
        "gradingGroups": [
            {
                "groupName": "MT1",
                "grade": 96,
                "weight": 20
            },
            {
                "groupName": "MT2",
                "grade": 0,
                "weight": 0
            },
            {
                "groupName": "Final",
                "grade": 0,
                "weight": 0
            },
            {
                "groupName": "HW",
                "grade": 100,
                "weight": 10
            }
        ]
    }
]}